flask_openai/__init__.py
flask_openai-0.5.0.dist-info/LICENSE
flask_openai-0.5.0.dist-info/WHEEL
flask_openai-0.5.0.dist-info/METADATA
flask_openai-0.5.0.dist-info/RECORD
