Metadata-Version: 2.1
Name: flask-openai
Version: 0.5.0
Summary: A Flask extension for easy integration with OpenAI's API.
Author-email: Nidal Alhariri <level09@gmail.com>
Requires-Python: >=3.7
Classifier: Framework :: Flask
Classifier: License :: OSI Approved :: MIT License
Classifier: Programming Language :: Python :: 3
Classifier: Programming Language :: Python :: 3.7
Classifier: Programming Language :: Python :: 3.8
Classifier: Programming Language :: Python :: 3.9
Classifier: Programming Language :: Python :: 3.10
Classifier: Programming Language :: Python :: 3.11
Classifier: Programming Language :: Python :: 3.12
Classifier: Intended Audience :: Developers
Classifier: Topic :: Software Development :: Libraries :: Python Modules
Requires-Dist: flask >=3.0.0
Requires-Dist: openai >=0.27.0
Project-URL: Home, https://github.com/level09/flask-openai
